{
  "03E02005-EFA6-48D6-8A76-05B2822A74E9" : {
    "objectMetadataList" : [

    ]
  },
  "0A9B4653-B11E-4D6A-850E-C6FCB621626C" : {
    "objectMetadataList" : [
      [
        "0A9B4653-B11E-4D6A-850E-C6FCB621626C",
        "Root"
      ],
      {
        "isExpanded" : true,
        "isLocked" : false
      },
      [
        "0A9B4653-B11E-4D6A-850E-C6FCB621626C",
        "Root",
        "Sphere"
      ],
      {
        "isExpanded" : true,
        "isLocked" : false
      },
      [
        "0A9B4653-B11E-4D6A-850E-C6FCB621626C",
        "Root",
        "GridMaterial"
      ],
      {
        "isExpanded" : true,
        "isLocked" : false
      }
    ]
  },
  "1CBF3893-ABFD-408C-8B91-045BFD257808" : {
    "objectMetadataList" : [

    ]
  },
  "26DBAE76-5DD8-47B6-A085-1B4ADA111097" : {
    "objectMetadataList" : [
      [
        "26DBAE76-5DD8-47B6-A085-1B4ADA111097",
        "Root"
      ],
      {
        "isExpanded" : true,
        "isLocked" : false
      }
    ]
  },
  "34C460AE-CA1B-4348-BD05-621ACBDFFE97" : {
    "objectMetadataList" : [

    ]
  },
  "440DE5B4-E4E4-459B-AABF-9ACE96319272" : {
    "objectMetadataList" : [
      [
        "440DE5B4-E4E4-459B-AABF-9ACE96319272",
        "Root"
      ],
      {
        "isExpanded" : true,
        "isLocked" : false
      }
    ]
  },
  "7C47133F-116A-45E9-A795-0BB27FFD4F67" : {
    "objectMetadataList" : [
      [
        "7C47133F-116A-45E9-A795-0BB27FFD4F67",
        "root",
        "baseball_bat"
      ],
      {
        "isExpanded" : true,
        "isLocked" : false
      },
      [
        "7C47133F-116A-45E9-A795-0BB27FFD4F67",
        "root"
      ],
      {
        "isExpanded" : true,
        "isLocked" : false
      }
    ]
  },
  "A10EA290-87F0-40C8-AF6C-473D4615150D" : {
    "objectMetadataList" : [
      [
        "A10EA290-87F0-40C8-AF6C-473D4615150D",
        "Root",
        "Chamber"
      ],
      {
        "isExpanded" : false,
        "isLocked" : false
      },
      [
        "A10EA290-87F0-40C8-AF6C-473D4615150D",
        "Root"
      ],
      {
        "isExpanded" : true,
        "isLocked" : false
      },
      [
        "A10EA290-87F0-40C8-AF6C-473D4615150D",
        "Root",
        "baseballBat"
      ],
      {
        "disallowsFraming" : false,
        "isExpanded" : false,
        "isLocked" : false,
        "selectedAudioFilePrim" : {
          "string" : "\/Root\/tam_xa_mai_56766_mp3"
        }
      }
    ]
  },
  "D4A673C6-41BA-4D3E-8FE3-B014BF143B9C" : {
    "objectMetadataList" : [
      [
        "D4A673C6-41BA-4D3E-8FE3-B014BF143B9C",
        "Root"
      ],
      {
        "isExpanded" : true,
        "isLocked" : false
      },
      [
        "D4A673C6-41BA-4D3E-8FE3-B014BF143B9C",
        "Root",
        "AmbientAudio"
      ],
      {
        "isExpanded" : false,
        "isLocked" : false,
        "selectedAudioFilePrim" : {
          "string" : "\/Root\/backgroundMusic_mp3"
        }
      }
    ]
  },
  "FBD8436F-6B8B-4B82-99B5-995D538B4704" : {
    "objectMetadataList" : [
      [
        "FBD8436F-6B8B-4B82-99B5-995D538B4704",
        "Root"
      ],
      {
        "isExpanded" : true,
        "isLocked" : false
      }
    ]
  }
}